Workbook

Sheet Юнитка
A1: № | B1: Артикул ВБ | C1: Артикул продавца | D1: Бренд | E1: Название | F1: Остаток FBO | G1: Остаток FBS | H1: Остаток поставщика | I1: Комментарий | J1: Заказы 7д | K1: Цена закупки | L1: Цена продажи | M1: Цена базовая | N1: % скидки | O1: Цена продажи кальк. | P1: Прибыль FBO кальк. | Q1: Рентаб. FBO кальк.% | R1: Прибыль FBS кальк. | S1: Рентаб. FBS кальк.% | T1: Наша цена на ВБ | U1: СПП | V1: % Выкупа | W1: Длина | X1: Ширина | Y1: Высота | Z1: Объём | AA1: Коэфф. склада | AB1: Доставка базовая | AC1: Доставка с возвратом | AD1: Налог УСН % | AE1: Налог ₽ | AF1: Доп. комиссия % | AG1: Комиссия FBO кат.% | AH1: Комиссия FBO итог% | AI1: Комиссия FBO ₽ | AJ1: Комиссия FBS кат.% | AK1: Комиссия FBS итог% | AL1: Комиссия FBS ₽ | AM1: Упаковка | AN1: Хранение | AO1: Брак % | AP1: Брак ₽ | AQ1: Прибыль FBO | AR1: Маржа FBO % | AS1: Рентаб. FBO % | AT1: Прибыль FBS | AU1: Маржа FBS % | AV1: Рентаб. FBS %
A2: =ROW()-1 | K2: =IFERROR(INDEX('_Цены_закупки'!$B:$B;MATCH(C2;'_Цены_закупки'!$A:$A;0));"") | N2: =IF(AND(M2>0;L2>0);1-L2/M2;"") | O2: =IF(OR(Q2="";K2=0);"";(K2+IF(AM2>0;AM2;'_Настройки'!$B$9)+AP2+AC2+Q2*K2)/(1-AH2-AD2)) | P2: =IF(O2="";"";O2-K2-O2*AH2-O2*AD2-IF(AM2>0;AM2;'_Настройки'!$B$9)-AP2-AC2) | Q2: =IF(AND(O2>0;K2>0);P2/K2;"") | R2: =IF(O2="";"";O2-K2-O2*AK2-O2*AD2-IF(AM2>0;AM2;'_Настройки'!$B$9)-AP2-AC2) | S2: =IF(AND(O2>0;K2>0);R2/K2;"") | U2: =IF(AND(L2>0;T2>0);1-T2/L2;"") | V2: ='_Настройки'!$B$4 | Z2: =IF(AND(W2>0;X2>0;Y2>0);W2*X2*Y2/1000;"") | AB2: =('_Настройки'!$B$6+MAX(0;Z2-1)*'_Настройки'!$B$7)*IF(AA2>0;AA2;'_Настройки'!$B$10) | AC2: =AB2*(1+'_Настройки'!$B$8) | AD2: ='_Настройки'!$B$2 | AE2: =L2*AD2 | AF2: ='_Настройки'!$B$3 | AG2: =IFERROR(INDEX('_Комиссия_ВБ'!$B:$B;MATCH(C2;'_Комиссия_ВБ'!$A:$A;0));0,245) | AH2: =AG2+AF2 | AI2: =L2*AH2 | AJ2: =IFERROR(INDEX('_Комиссия_ВБ'!$C:$C;MATCH(C2;'_Комиссия_ВБ'!$A:$A;0));0,28) | AK2: =AJ2+AF2 | AL2: =L2*AK2 | AO2: ='_Настройки'!$B$5 | AP2: =IF(K2>0;K2*AO2;0) | AQ2: =L2-K2-AI2-AE2-IF(AM2>0;AM2;'_Настройки'!$B$9)-AP2-AC2 | AR2: =IF(L2>0;AQ2/L2;"") | AS2: =IF(K2>0;AQ2/K2;"") | AT2: =L2-K2-AL2-AE2-IF(AM2>0;AM2;'_Настройки'!$B$9)-AP2-AC2 | AU2: =IF(L2>0;AT2/L2;"") | AV2: =IF(K2>0;AT2/K2;"")
A3: =ROW()-1 | K3: =IFERROR(INDEX('_Цены_закупки'!$B:$B;MATCH(C3;'_Цены_закупки'!$A:$A;0));"") | N3: =IF(AND(M3>0;L3>0);1-L3/M3;"") | O3: =IF(OR(Q3="";K3=0);"";(K3+IF(AM3>0;AM3;'_Настройки'!$B$9)+AP3+AC3+Q3*K3)/(1-AH3-AD3)) | P3: =IF(O3="";"";O3-K3-O3*AH3-O3*AD3-IF(AM3>0;AM3;'_Настройки'!$B$9)-AP3-AC3) | Q3: =IF(AND(O3>0;K3>0);P3/K3;"") | R3: =IF(O3="";"";O3-K3-O3*AK3-O3*AD3-IF(AM3>0;AM3;'_Настройки'!$B$9)-AP3-AC3) | S3: =IF(AND(O3>0;K3>0);R3/K3;"") | U3: =IF(AND(L3>0;T3>0);1-T3/L3;"") | V3: ='_Настройки'!$B$4 | Z3: =IF(AND(W3>0;X3>0;Y3>0);W3*X3*Y3/1000;"") | AB3: =('_Настройки'!$B$6+MAX(0;Z3-1)*'_Настройки'!$B$7)*IF(AA3>0;AA3;'_Настройки'!$B$10) | AC3: =AB3*(1+'_Настройки'!$B$8) | AD3: ='_Настройки'!$B$2 | AE3: =L3*AD3 | AF3: ='_Настройки'!$B$3 | AG3: =IFERROR(INDEX('_Комиссия_ВБ'!$B:$B;MATCH(C3;'_Комиссия_ВБ'!$A:$A;0));0,245) | AH3: =AG3+AF3 | AI3: =L3*AH3 | AJ3: =IFERROR(INDEX('_Комиссия_ВБ'!$C:$C;MATCH(C3;'_Комиссия_ВБ'!$A:$A;0));0,28) | AK3: =AJ3+AF3 | AL3: =L3*AK3 | AO3: ='_Настройки'!$B$5 | AP3: =IF(K3>0;K3*AO3;0) | AQ3: =L3-K3-AI3-AE3-IF(AM3>0;AM3;'_Настройки'!$B$9)-AP3-AC3 | AR3: =IF(L3>0;AQ3/L3;"") | AS3: =IF(K3>0;AQ3/K3;"") | AT3: =L3-K3-AL3-AE3-IF(AM3>0;AM3;'_Настройки'!$B$9)-AP3-AC3 | AU3: =IF(L3>0;AT3/L3;"") | AV3: =IF(K3>0;AT3/K3;"")
A4: =ROW()-1 | K4: =IFERROR(INDEX('_Цены_закупки'!$B:$B;MATCH(C4;'_Цены_закупки'!$A:$A;0));"") | N4: =IF(AND(M4>0;L4>0);1-L4/M4;"") | O4: =IF(OR(Q4="";K4=0);"";(K4+IF(AM4>0;AM4;'_Настройки'!$B$9)+AP4+AC4+Q4*K4)/(1-AH4-AD4)) | P4: =IF(O4="";"";O4-K4-O4*AH4-O4*AD4-IF(AM4>0;AM4;'_Настройки'!$B$9)-AP4-AC4) | Q4: =IF(AND(O4>0;K4>0);P4/K4;"") | R4: =IF(O4="";"";O4-K4-O4*AK4-O4*AD4-IF(AM4>0;AM4;'_Настройки'!$B$9)-AP4-AC4) | S4: =IF(AND(O4>0;K4>0);R4/K4;"") | U4: =IF(AND(L4>0;T4>0);1-T4/L4;"") | V4: ='_Настройки'!$B$4 | Z4: =IF(AND(W4>0;X4>0;Y4>0);W4*X4*Y4/1000;"") | AB4: =('_Настройки'!$B$6+MAX(0;Z4-1)*'_Настройки'!$B$7)*IF(AA4>0;AA4;'_Настройки'!$B$10) | AC4: =AB4*(1+'_Настройки'!$B$8) | AD4: ='_Настройки'!$B$2 | AE4: =L4*AD4 | AF4: ='_Настройки'!$B$3 | AG4: =IFERROR(INDEX('_Комиссия_ВБ'!$B:$B;MATCH(C4;'_Комиссия_ВБ'!$A:$A;0));0,245) | AH4: =AG4+AF4 | AI4: =L4*AH4 | AJ4: =IFERROR(INDEX('_Комиссия_ВБ'!$C:$C;MATCH(C4;'_Комиссия_ВБ'!$A:$A;0));0,28) | AK4: =AJ4+AF4 | AL4: =L4*AK4 | AO4: ='_Настройки'!$B$5 | AP4: =IF(K4>0;K4*AO4;0) | AQ4: =L4-K4-AI4-AE4-IF(AM4>0;AM4;'_Настройки'!$B$9)-AP4-AC4 | AR4: =IF(L4>0;AQ4/L4;"") | AS4: =IF(K4>0;AQ4/K4;"") | AT4: =L4-K4-AL4-AE4-IF(AM4>0;AM4;'_Настройки'!$B$9)-AP4-AC4 | AU4: =IF(L4>0;AT4/L4;"") | AV4: =IF(K4>0;AT4/K4;"")
A5: =ROW()-1 | K5: =IFERROR(INDEX('_Цены_закупки'!$B:$B;MATCH(C5;'_Цены_закупки'!$A:$A;0));"") | N5: =IF(AND(M5>0;L5>0);1-L5/M5;"") | O5: =IF(OR(Q5="";K5=0);"";(K5+IF(AM5>0;AM5;'_Настройки'!$B$9)+AP5+AC5+Q5*K5)/(1-AH5-AD5)) | P5: =IF(O5="";"";O5-K5-O5*AH5-O5*AD5-IF(AM5>0;AM5;'_Настройки'!$B$9)-AP5-AC5) | Q5: =IF(AND(O5>0;K5>0);P5/K5;"") | R5: =IF(O5="";"";O5-K5-O5*AK5-O5*AD5-IF(AM5>0;AM5;'_Настройки'!$B$9)-AP5-AC5) | S5: =IF(AND(O5>0;K5>0);R5/K5;"") | U5: =IF(AND(L5>0;T5>0);1-T5/L5;"") | V5: ='_Настройки'!$B$4 | Z5: =IF(AND(W5>0;X5>0;Y5>0);W5*X5*Y5/1000;"") | AB5: =('_Настройки'!$B$6+MAX(0;Z5-1)*'_Настройки'!$B$7)*IF(AA5>0;AA5;'_Настройки'!$B$10) | AC5: =AB5*(1+'_Настройки'!$B$8) | AD5: ='_Настройки'!$B$2 | AE5: =L5*AD5 | AF5: ='_Настройки'!$B$3 | AG5: =IFERROR(INDEX('_Комиссия_ВБ'!$B:$B;MATCH(C5;'_Комиссия_ВБ'!$A:$A;0));0,245) | AH5: =AG5+AF5 | AI5: =L5*AH5 | AJ5: =IFERROR(INDEX('_Комиссия_ВБ'!$C:$C;MATCH(C5;'_Комиссия_ВБ'!$A:$A;0));0,28) | AK5: =AJ5+AF5 | AL5: =L5*AK5 | AO5: ='_Настройки'!$B$5 | AP5: =IF(K5>0;K5*AO5;0) | AQ5: =L5-K5-AI5-AE5-IF(AM5>0;AM5;'_Настройки'!$B$9)-AP5-AC5 | AR5: =IF(L5>0;AQ5/L5;"") | AS5: =IF(K5>0;AQ5/K5;"") | AT5: =L5-K5-AL5-AE5-IF(AM5>0;AM5;'_Настройки'!$B$9)-AP5-AC5 | AU5: =IF(L5>0;AT5/L5;"") | AV5: =IF(K5>0;AT5/K5;"")
A6: =ROW()-1 | K6: =IFERROR(INDEX('_Цены_закупки'!$B:$B;MATCH(C6;'_Цены_закупки'!$A:$A;0));"") | N6: =IF(AND(M6>0;L6>0);1-L6/M6;"") | O6: =IF(OR(Q6="";K6=0);"";(K6+IF(AM6>0;AM6;'_Настройки'!$B$9)+AP6+AC6+Q6*K6)/(1-AH6-AD6)) | P6: =IF(O6="";"";O6-K6-O6*AH6-O6*AD6-IF(AM6>0;AM6;'_Настройки'!$B$9)-AP6-AC6) | Q6: =IF(AND(O6>0;K6>0);P6/K6;"") | R6: =IF(O6="";"";O6-K6-O6*AK6-O6*AD6-IF(AM6>0;AM6;'_Настройки'!$B$9)-AP6-AC6) | S6: =IF(AND(O6>0;K6>0);R6/K6;"") | U6: =IF(AND(L6>0;T6>0);1-T6/L6;"") | V6: ='_Настройки'!$B$4 | Z6: =IF(AND(W6>0;X6>0;Y6>0);W6*X6*Y6/1000;"") | AB6: =('_Настройки'!$B$6+MAX(0;Z6-1)*'_Настройки'!$B$7)*IF(AA6>0;AA6;'_Настройки'!$B$10) | AC6: =AB6*(1+'_Настройки'!$B$8) | AD6: ='_Настройки'!$B$2 | AE6: =L6*AD6 | AF6: ='_Настройки'!$B$3 | AG6: =IFERROR(INDEX('_Комиссия_ВБ'!$B:$B;MATCH(C6;'_Комиссия_ВБ'!$A:$A;0));0,245) | AH6: =AG6+AF6 | AI6: =L6*AH6 | AJ6: =IFERROR(INDEX('_Комиссия_ВБ'!$C:$C;MATCH(C6;'_Комиссия_ВБ'!$A:$A;0));0,28) | AK6: =AJ6+AF6 | AL6: =L6*AK6 | AO6: ='_Настройки'!$B$5 | AP6: =IF(K6>0;K6*AO6;0) | AQ6: =L6-K6-AI6-AE6-IF(AM6>0;AM6;'_Настройки'!$B$9)-AP6-AC6 | AR6: =IF(L6>0;AQ6/L6;"") | AS6: =IF(K6>0;AQ6/K6;"") | AT6: =L6-K6-AL6-AE6-IF(AM6>0;AM6;'_Настройки'!$B$9)-AP6-AC6 | AU6: =IF(L6>0;AT6/L6;"") | AV6: =IF(K6>0;AT6/K6;"")
A7: =ROW()-1 | K7: =IFERROR(INDEX('_Цены_закупки'!$B:$B;MATCH(C7;'_Цены_закупки'!$A:$A;0));"") | N7: =IF(AND(M7>0;L7>0);1-L7/M7;"") | O7: =IF(OR(Q7="";K7=0);"";(K7+IF(AM7>0;AM7;'_Настройки'!$B$9)+AP7+AC7+Q7*K7)/(1-AH7-AD7)) | P7: =IF(O7="";"";O7-K7-O7*AH7-O7*AD7-IF(AM7>0;AM7;'_Настройки'!$B$9)-AP7-AC7) | Q7: =IF(AND(O7>0;K7>0);P7/K7;"") | R7: =IF(O7="";"";O7-K7-O7*AK7-O7*AD7-IF(AM7>0;AM7;'_Настройки'!$B$9)-AP7-AC7) | S7: =IF(AND(O7>0;K7>0);R7/K7;"") | U7: =IF(AND(L7>0;T7>0);1-T7/L7;"") | V7: ='_Настройки'!$B$4 | Z7: =IF(AND(W7>0;X7>0;Y7>0);W7*X7*Y7/1000;"") | AB7: =('_Настройки'!$B$6+MAX(0;Z7-1)*'_Настройки'!$B$7)*IF(AA7>0;AA7;'_Настройки'!$B$10) | AC7: =AB7*(1+'_Настройки'!$B$8) | AD7: ='_Настройки'!$B$2 | AE7: =L7*AD7 | AF7: ='_Настройки'!$B$3 | AG7: =IFERROR(INDEX('_Комиссия_ВБ'!$B:$B;MATCH(C7;'_Комиссия_ВБ'!$A:$A;0));0,245) | AH7: =AG7+AF7 | AI7: =L7*AH7 | AJ7: =IFERROR(INDEX('_Комиссия_ВБ'!$C:$C;MATCH(C7;'_Комиссия_ВБ'!$A:$A;0));0,28) | AK7: =AJ7+AF7 | AL7: =L7*AK7 | AO7: ='_Настройки'!$B$5 | AP7: =IF(K7>0;K7*AO7;0) | AQ7: =L7-K7-AI7-AE7-IF(AM7>0;AM7;'_Настройки'!$B$9)-AP7-AC7 | AR7: =IF(L7>0;AQ7/L7;"") | AS7: =IF(K7>0;AQ7/K7;"") | AT7: =L7-K7-AL7-AE7-IF(AM7>0;AM7;'_Настройки'!$B$9)-AP7-AC7 | AU7: =IF(L7>0;AT7/L7;"") | AV7: =IF(K7>0;AT7/K7;"")
A8: =ROW()-1 | K8: =IFERROR(INDEX('_Цены_закупки'!$B:$B;MATCH(C8;'_Цены_закупки'!$A:$A;0));"") | N8: =IF(AND(M8>0;L8>0);1-L8/M8;"") | O8: =IF(OR(Q8="";K8=0);"";(K8+IF(AM8>0;AM8;'_Настройки'!$B$9)+AP8+AC8+Q8*K8)/(1-AH8-AD8)) | P8: =IF(O8="";"";O8-K8-O8*AH8-O8*AD8-IF(AM8>0;AM8;'_Настройки'!$B$9)-AP8-AC8) | Q8: =IF(AND(O8>0;K8>0);P8/K8;"") | R8: =IF(O8="";"";O8-K8-O8*AK8-O8*AD8-IF(AM8>0;AM8;'_Настройки'!$B$9)-AP8-AC8) | S8: =IF(AND(O8>0;K8>0);R8/K8;"") | U8: =IF(AND(L8>0;T8>0);1-T8/L8;"") | V8: ='_Настройки'!$B$4 | Z8: =IF(AND(W8>0;X8>0;Y8>0);W8*X8*Y8/1000;"") | AB8: =('_Настройки'!$B$6+MAX(0;Z8-1)*'_Настройки'!$B$7)*IF(AA8>0;AA8;'_Настройки'!$B$10) | AC8: =AB8*(1+'_Настройки'!$B$8) | AD8: ='_Настройки'!$B$2 | AE8: =L8*AD8 | AF8: ='_Настройки'!$B$3 | AG8: =IFERROR(INDEX('_Комиссия_ВБ'!$B:$B;MATCH(C8;'_Комиссия_ВБ'!$A:$A;0));0,245) | AH8: =AG8+AF8 | AI8: =L8*AH8 | AJ8: =IFERROR(INDEX('_Комиссия_ВБ'!$C:$C;MATCH(C8;'_Комиссия_ВБ'!$A:$A;0));0,28) | AK8: =AJ8+AF8 | AL8: =L8*AK8 | AO8: ='_Настройки'!$B$5 | AP8: =IF(K8>0;K8*AO8;0) | AQ8: =L8-K8-AI8-AE8-IF(AM8>0;AM8;'_Настройки'!$B$9)-AP8-AC8 | AR8: =IF(L8>0;AQ8/L8;"") | AS8: =IF(K8>0;AQ8/K8;"") | AT8: =L8-K8-AL8-AE8-IF(AM8>0;AM8;'_Настройки'!$B$9)-AP8-AC8 | AU8: =IF(L8>0;AT8/L8;"") | AV8: =IF(K8>0;AT8/K8;"")
A9: =ROW()-1 | K9: =IFERROR(INDEX('_Цены_закупки'!$B:$B;MATCH(C9;'_Цены_закупки'!$A:$A;0));"") | N9: =IF(AND(M9>0;L9>0);1-L9/M9;"") | O9: =IF(OR(Q9="";K9=0);"";(K9+IF(AM9>0;AM9;'_Настройки'!$B$9)+AP9+AC9+Q9*K9)/(1-AH9-AD9)) | P9: =IF(O9="";"";O9-K9-O9*AH9-O9*AD9-IF(AM9>0;AM9;'_Настройки'!$B$9)-AP9-AC9) | Q9: =IF(AND(O9>0;K9>0);P9/K9;"") | R9: =IF(O9="";"";O9-K9-O9*AK9-O9*AD9-IF(AM9>0;AM9;'_Настройки'!$B$9)-AP9-AC9) | S9: =IF(AND(O9>0;K9>0);R9/K9;"") | U9: =IF(AND(L9>0;T9>0);1-T9/L9;"") | V9: ='_Настройки'!$B$4 | Z9: =IF(AND(W9>0;X9>0;Y9>0);W9*X9*Y9/1000;"") | AB9: =('_Настройки'!$B$6+MAX(0;Z9-1)*'_Настройки'!$B$7)*IF(AA9>0;AA9;'_Настройки'!$B$10) | AC9: =AB9*(1+'_Настройки'!$B$8) | AD9: ='_Настройки'!$B$2 | AE9: =L9*AD9 | AF9: ='_Настройки'!$B$3 | AG9: =IFERROR(INDEX('_Комиссия_ВБ'!$B:$B;MATCH(C9;'_Комиссия_ВБ'!$A:$A;0));0,245) | AH9: =AG9+AF9 | AI9: =L9*AH9 | AJ9: =IFERROR(INDEX('_Комиссия_ВБ'!$C:$C;MATCH(C9;'_Комиссия_ВБ'!$A:$A;0));0,28) | AK9: =AJ9+AF9 | AL9: =L9*AK9 | AO9: ='_Настройки'!$B$5 | AP9: =IF(K9>0;K9*AO9;0) | AQ9: =L9-K9-AI9-AE9-IF(AM9>0;AM9;'_Настройки'!$B$9)-AP9-AC9 | AR9: =IF(L9>0;AQ9/L9;"") | AS9: =IF(K9>0;AQ9/K9;"") | AT9: =L9-K9-AL9-AE9-IF(AM9>0;AM9;'_Настройки'!$B$9)-AP9-AC9 | AU9: =IF(L9>0;AT9/L9;"") | AV9: =IF(K9>0;AT9/K9;"")
A10: =ROW()-1 | K10: =IFERROR(INDEX('_Цены_закупки'!$B:$B;MATCH(C10;'_Цены_закупки'!$A:$A;0));"") | N10: =IF(AND(M10>0;L10>0);1-L10/M10;"") | O10: =IF(OR(Q10="";K10=0);"";(K10+IF(AM10>0;AM10;'_Настройки'!$B$9)+AP10+AC10+Q10*K10)/(1-AH10-AD10)) | P10: =IF(O10="";"";O10-K10-O10*AH10-O10*AD10-IF(AM10>0;AM10;'_Настройки'!$B$9)-AP10-AC10) | Q10: =IF(AND(O10>0;K10>0);P10/K10;"") | R10: =IF(O10="";"";O10-K10-O10*AK10-O10*AD10-IF(AM10>0;AM10;'_Настройки'!$B$9)-AP10-AC10) | S10: =IF(AND(O10>0;K10>0);R10/K10;"") | U10: =IF(AND(L10>0;T10>0);1-T10/L10;"") | V10: ='_Настройки'!$B$4 | Z10: =IF(AND(W10>0;X10>0;Y10>0);W10*X10*Y10/1000;"") | AB10: =('_Настройки'!$B$6+MAX(0;Z10-1)*'_Настройки'!$B$7)*IF(AA10>0;AA10;'_Настройки'!$B$10) | AC10: =AB10*(1+'_Настройки'!$B$8) | AD10: ='_Настройки'!$B$2 | AE10: =L10*AD10 | AF10: ='_Настройки'!$B$3 | AG10: =IFERROR(INDEX('_Комиссия_ВБ'!$B:$B;MATCH(C10;'_Комиссия_ВБ'!$A:$A;0));0,245) | AH10: =AG10+AF10 | AI10: =L10*AH10 | AJ10: =IFERROR(INDEX('_Комиссия_ВБ'!$C:$C;MATCH(C10;'_Комиссия_ВБ'!$A:$A;0));0,28) | AK10: =AJ10+AF10 | AL10: =L10*AK10 | AO10: ='_Настройки'!$B$5 | AP10: =IF(K10>0;K10*AO10;0) | AQ10: =L10-K10-AI10-AE10-IF(AM10>0;AM10;'_Настройки'!$B$9)-AP10-AC10 | AR10: =IF(L10>0;AQ10/L10;"") | AS10: =IF(K10>0;AQ10/K10;"") | AT10: =L10-K10-AL10-AE10-IF(AM10>0;AM10;'_Настройки'!$B$9)-AP10-AC10 | AU10: =IF(L10>0;AT10/L10;"") | AV10: =IF(K10>0;AT10/K10;"")
A11: =ROW()-1 | K11: =IFERROR(INDEX('_Цены_закупки'!$B:$B;MATCH(C11;'_Цены_закупки'!$A:$A;0));"") | N11: =IF(AND(M11>0;L11>0);1-L11/M11;"") | O11: =IF(OR(Q11="";K11=0);"";(K11+IF(AM11>0;AM11;'_Настройки'!$B$9)+AP11+AC11+Q11*K11)/(1-AH11-AD11)) | P11: =IF(O11="";"";O11-K11-O11*AH11-O11*AD11-IF(AM11>0;AM11;'_Настройки'!$B$9)-AP11-AC11) | Q11: =IF(AND(O11>0;K11>0);P11/K11;"") | R11: =IF(O11="";"";O11-K11-O11*AK11-O11*AD11-IF(AM11>0;AM11;'_Настройки'!$B$9)-AP11-AC11) | S11: =IF(AND(O11>0;K11>0);R11/K11;"") | U11: =IF(AND(L11>0;T11>0);1-T11/L11;"") | V11: ='_Настройки'!$B$4 | Z11: =IF(AND(W11>0;X11>0;Y11>0);W11*X11*Y11/1000;"") | AB11: =('_Настройки'!$B$6+MAX(0;Z11-1)*'_Настройки'!$B$7)*IF(AA11>0;AA11;'_Настройки'!$B$10) | AC11: =AB11*(1+'_Настройки'!$B$8) | AD11: ='_Настройки'!$B$2 | AE11: =L11*AD11 | AF11: ='_Настройки'!$B$3 | AG11: =IFERROR(INDEX('_Комиссия_ВБ'!$B:$B;MATCH(C11;'_Комиссия_ВБ'!$A:$A;0));0,245) | AH11: =AG11+AF11 | AI11: =L11*AH11 | AJ11: =IFERROR(INDEX('_Комиссия_ВБ'!$C:$C;MATCH(C11;'_Комиссия_ВБ'!$A:$A;0));0,28) | AK11: =AJ11+AF11 | AL11: =L11*AK11 | AO11: ='_Настройки'!$B$5 | AP11: =IF(K11>0;K11*AO11;0) | AQ11: =L11-K11-AI11-AE11-IF(AM11>0;AM11;'_Настройки'!$B$9)-AP11-AC11 | AR11: =IF(L11>0;AQ11/L11;"") | AS11: =IF(K11>0;AQ11/K11;"") | AT11: =L11-K11-AL11-AE11-IF(AM11>0;AM11;'_Настройки'!$B$9)-AP11-AC11 | AU11: =IF(L11>0;AT11/L11;"") | AV11: =IF(K11>0;AT11/K11;"")
A12: =ROW()-1 | K12: =IFERROR(INDEX('_Цены_закупки'!$B:$B;MATCH(C12;'_Цены_закупки'!$A:$A;0));"") | N12: =IF(AND(M12>0;L12>0);1-L12/M12;"") | O12: =IF(OR(Q12="";K12=0);"";(K12+IF(AM12>0;AM12;'_Настройки'!$B$9)+AP12+AC12+Q12*K12)/(1-AH12-AD12)) | P12: =IF(O12="";"";O12-K12-O12*AH12-O12*AD12-IF(AM12>0;AM12;'_Настройки'!$B$9)-AP12-AC12) | Q12: =IF(AND(O12>0;K12>0);P12/K12;"") | R12: =IF(O12="";"";O12-K12-O12*AK12-O12*AD12-IF(AM12>0;AM12;'_Настройки'!$B$9)-AP12-AC12) | S12: =IF(AND(O12>0;K12>0);R12/K12;"") | U12: =IF(AND(L12>0;T12>0);1-T12/L12;"") | V12: ='_Настройки'!$B$4 | Z12: =IF(AND(W12>0;X12>0;Y12>0);W12*X12*Y12/1000;"") | AB12: =('_Настройки'!$B$6+MAX(0;Z12-1)*'_Настройки'!$B$7)*IF(AA12>0;AA12;'_Настройки'!$B$10) | AC12: =AB12*(1+'_Настройки'!$B$8) | AD12: ='_Настройки'!$B$2 | AE12: =L12*AD12 | AF12: ='_Настройки'!$B$3 | AG12: =IFERROR(INDEX('_Комиссия_ВБ'!$B:$B;MATCH(C12;'_Комиссия_ВБ'!$A:$A;0));0,245) | AH12: =AG12+AF12 | AI12: =L12*AH12 | AJ12: =IFERROR(INDEX('_Комиссия_ВБ'!$C:$C;MATCH(C12;'_Комиссия_ВБ'!$A:$A;0));0,28) | AK12: =AJ12+AF12 | AL12: =L12*AK12 | AO12: ='_Настройки'!$B$5 | AP12: =IF(K12>0;K12*AO12;0) | AQ12: =L12-K12-AI12-AE12-IF(AM12>0;AM12;'_Настройки'!$B$9)-AP12-AC12 | AR12: =IF(L12>0;AQ12/L12;"") | AS12: =IF(K12>0;AQ12/K12;"") | AT12: =L12-K12-AL12-AE12-IF(AM12>0;AM12;'_Настройки'!$B$9)-AP12-AC12 | AU12: =IF(L12>0;AT12/L12;"") | AV12: =IF(K12>0;AT12/K12;"")
A13: =ROW()-1 | K13: =IFERROR(INDEX('_Цены_закупки'!$B:$B;MATCH(C13;'_Цены_закупки'!$A:$A;0));"") | N13: =IF(AND(M13>0;L13>0);1-L13/M13;"") | O13: =IF(OR(Q13="";K13=0);"";(K13+IF(AM13>0;AM13;'_Настройки'!$B$9)+AP13+AC13+Q13*K13)/(1-AH13-AD13)) | P13: =IF(O13="";"";O13-K13-O13*AH13-O13*AD13-IF(AM13>0;AM13;'_Настройки'!$B$9)-AP13-AC13) | Q13: =IF(AND(O13>0;K13>0);P13/K13;"") | R13: =IF(O13="";"";O13-K13-O13*AK13-O13*AD13-IF(AM13>0;AM13;'_Настройки'!$B$9)-AP13-AC13) | S13: =IF(AND(O13>0;K13>0);R13/K13;"") | U13: =IF(AND(L13>0;T13>0);1-T13/L13;"") | V13: ='_Настройки'!$B$4 | Z13: =IF(AND(W13>0;X13>0;Y13>0);W13*X13*Y13/1000;"") | AB13: =('_Настройки'!$B$6+MAX(0;Z13-1)*'_Настройки'!$B$7)*IF(AA13>0;AA13;'_Настройки'!$B$10) | AC13: =AB13*(1+'_Настройки'!$B$8) | AD13: ='_Настройки'!$B$2 | AE13: =L13*AD13 | AF13: ='_Настройки'!$B$3 | AG13: =IFERROR(INDEX('_Комиссия_ВБ'!$B:$B;MATCH(C13;'_Комиссия_ВБ'!$A:$A;0));0,245) | AH13: =AG13+AF13 | AI13: =L13*AH13 | AJ13: =IFERROR(INDEX('_Комиссия_ВБ'!$C:$C;MATCH(C13;'_Комиссия_ВБ'!$A:$A;0));0,28) | AK13: =AJ13+AF13 | AL13: =L13*AK13 | AO13: ='_Настройки'!$B$5 | AP13: =IF(K13>0;K13*AO13;0) | AQ13: =L13-K13-AI13-AE13-IF(AM13>0;AM13;'_Настройки'!$B$9)-AP13-AC13 | AR13: =IF(L13>0;AQ13/L13;"") | AS13: =IF(K13>0;AQ13/K13;"") | AT13: =L13-K13-AL13-AE13-IF(AM13>0;AM13;'_Настройки'!$B$9)-AP13-AC13 | AU13: =IF(L13>0;AT13/L13;"") | AV13: =IF(K13>0;AT13/K13;"")
... A500: =ROW()-1 | K500: =IFERROR(INDEX('_Цены_закупки'!$B:$B;MATCH(C500;'_Цены_закупки'!$A:$A;0));"") | N500: =IF(AND(M500>0;L500>0);1-L500/M500;"") | O500: =IF(OR(Q500="";K500=0);"";(K500+IF(AM500>0;AM500;'_Настройки'!$B$9)+AP500+AC500+Q500*K500)/(1-AH500-AD500)) | P500: =IF(O500="";"";O500-K500-O500*AH500-O500*AD500-IF(AM500>0;AM500;'_Настройки'!$B$9)-AP500-AC500) | Q500: =IF(AND(O500>0;K500>0);P500/K500;"") | R500: =IF(O500="";"";O500-K500-O500*AK500-O500*AD500-IF(AM500>0;AM500;'_Настройки'!$B$9)-AP500-AC500) | S500: =IF(AND(O500>0;K500>0);R500/K500;"") | U500: =IF(AND(L500>0;T500>0);1-T500/L500;"") | V500: ='_Настройки'!$B$4 | Z500: =IF(AND(W500>0;X500>0;Y500>0);W500*X500*Y500/1000;"") | AB500: =('_Настройки'!$B$6+MAX(0;Z500-1)*'_Настройки'!$B$7)*IF(AA500>0;AA500;'_Настройки'!$B$10) | AC500: =AB500*(1+'_Настройки'!$B$8) | AD500: ='_Настройки'!$B$2 | AE500: =L500*AD500 | AF500: ='_Настройки'!$B$3 | AG500: =IFERROR(INDEX('_Комиссия_ВБ'!$B:$B;MATCH(C500;'_Комиссия_ВБ'!$A:$A;0));0,245) | AH500: =AG500+AF500 | AI500: =L500*AH500 | AJ500: =IFERROR(INDEX('_Комиссия_ВБ'!$C:$C;MATCH(C500;'_Комиссия_ВБ'!$A:$A;0));0,28) | AK500: =AJ500+AF500 | AL500: =L500*AK500 | AO500: ='_Настройки'!$B$5 | AP500: =IF(K500>0;K500*AO500;0) | AQ500: =L500-K500-AI500-AE500-IF(AM500>0;AM500;'_Настройки'!$B$9)-AP500-AC500 | AR500: =IF(L500>0;AQ500/L500;"") | AS500: =IF(K500>0;AQ500/K500;"") | AT500: =L500-K500-AL500-AE500-IF(AM500>0;AM500;'_Настройки'!$B$9)-AP500-AC500 | AU500: =IF(L500>0;AT500/L500;"") | AV500: =IF(K500>0;AT500/K500;"")

Sheet _Настройки
A1: Параметр | B1: Значение | C1: Описание
A2: Налог УСН Доходы | B2: 0.11 | C2: Доля от цены продажи
A3: Доп. комиссия WB | B3: 0.0175 | C3: К категорийной комиссии
A4: % выкупа | B4: 0.9 | C4: Справочно
A5: Брак/потери | B5: 0.01 | C5: Доля от закупки
A6: Логистика: 1-й литр, ₽ | B6: 46 | C6: Тариф WB
A7: Логистика: доп. литр, ₽ | B7: 14 | C7: За литр сверх 1
A8: Наценка обратной логистики | B8: 0.0454 | C8: К базовой доставке
A9: Упаковка по умолчанию, ₽ | B9: 65 | C9: Если «Упаковка» пуста
A10: Коэфф. склада по умолчанию | B10: 2.2 | C10: Если «Коэфф.» пуст

Sheet _Цены_закупки
A1: Артикул продавца | B1: Цена закупки
A2: 69740.0 | B2: 162
A3: 61750.0 | B3: 183.33
A4: 61738 с черенком | B4: 166.84
A5: 617885.0 | B5: 994.2
A6: 61738.0 | B6: 166.84
A7: 61733.0 | B7: 794.28
A8: 61732.0 | B8: 589.47
A9: 61768.0 | B9: 271
A10: 69610.0 | B10: 3492.85
A11: 67461.0 | B11: 1632.51
A12: 617705.0 | B12: 228.92
A13: 61460.0 | B13: 492.76
... A502: PI-KWSG | B502: 1608

Sheet _Комиссия_ВБ
A1: Артикул продавца | B1: Комиссия FBO | C1: Комиссия FBS
A2: sahar | B2: 0.245 | C2: 0.28
A3: pocket400 | B3: 0.245 | C3: 0.28
A4: 63217.0 | B4: 0.295 | C4: 0.33
A5: KH-5885 | B5: 0.275 | C5: 0.31
A6: denzelpushka | B6: 0.285 | C6: 0.32
A7: 61744.0 | B7: 0.295 | C7: 0.33
A8: 42001.0 | B8: 0.315 | C8: 0.35
A9: KH-5886 | B9: 0.275 | C9: 0.31
A10: 689615-1 | B10: 0.295 | C10: 0.33
A11: мезороллер | B11: 0.315 | C11: 0.35
A12: 64302.0 | B12: 0.245 | C12: 0.245
A13: 21605.0 | B13: 0.295 | C13: 0.33
... A632: PI-KWSG | B632: 0.245 | C632: 0.28
